invoke_release/__init__.py
invoke_release/plugins.py
invoke_release/tasks.py
invoke_release/version.py
invoke_release-4.6.0.dist-info/LICENSE
invoke_release-4.6.0.dist-info/METADATA
invoke_release-4.6.0.dist-info/WHEEL
invoke_release-4.6.0.dist-info/top_level.txt
invoke_release-4.6.0.dist-info/RECORD
